README.md
setup.cfg
setup.py
sjb/__init__.py
sjb/constants.py
sjb/common/__init__.py
sjb/common/base.py
sjb/common/config.py
sjb/common/misc.py
sjb/cs/classes.py
sjb/cs/display.py
sjb/cs/fileio.py
sjb/cs/main.py
sjb/td/__init__.py
sjb/td/classes.py
sjb/td/display.py
sjb/td/fileio.py
sjb/td/main.py
sjb_tools.egg-info/PKG-INFO
sjb_tools.egg-info/SOURCES.txt
sjb_tools.egg-info/dependency_links.txt
sjb_tools.egg-info/entry_points.txt
sjb_tools.egg-info/requires.txt
sjb_tools.egg-info/top_level.txt