Metadata-Version: 1.2
Name: sjb-tools
Version: 0.1.3.dev0
Summary: A set of simple command line productivity tools.
Home-page: https://github.com/sicklybeans/sjb-tools
Author: Sam Bryant
Author-email: sbryant1014@gmail.com
License: MIT License
Platform: UNKNOWN
Classifier: Development Status :: 2 - Pre-Alpha
Classifier: Environment :: Console
Classifier: License :: OSI Approved :: MIT License
Classifier: Programming Language :: Python :: 3
Classifier: Topic :: Office/Business
Requires-Python: >=3
